__editable___cnc_centroid_skinning_1_5_30_finder.py
__editable__.cnc_centroid_skinning-1.5.30.pth
cnc_centroid_skinning-1.5.30.dist-info/licenses/LICENSE
cnc_centroid_skinning-1.5.30.dist-info/METADATA
cnc_centroid_skinning-1.5.30.dist-info/WHEEL
cnc_centroid_skinning-1.5.30.dist-info/entry_points.txt
cnc_centroid_skinning-1.5.30.dist-info/top_level.txt
cnc_centroid_skinning-1.5.30.dist-info/RECORD
