Metadata-Version: 2.4
Name: cnc_centroid_skinning
Version: 1.5.30
Summary: wrapper for the CncSkinning API (C#) 64 bits
Home-page: https://github.com/fca1/cnc_centroid_skinning/
Author: Frantz Capiez
Author-email: frantz.capiez@epi-rf.fr
License: MIT
Project-URL: Documentation, https://htmlpreview.github.io/?https://github.com/fca1/cnc_centroid_skinning/blob/master/cnc_centroid_skinning/doc/cnc_centroid_skinning/index.html
Project-URL: Source Code, https://github.com/fca1/cnc_centroid_skinning/tree/master/cnc_centroid_skinning/cnc_centroid_skinning/
Classifier: Development Status :: 2 - Pre-Alpha
Classifier: Programming Language :: Python :: 3.12
Classifier: Operating System :: Microsoft :: Windows :: Windows 11
Classifier: Topic :: Software Development :: Libraries
License-File: LICENSE
Requires-Dist: pythonnet
Requires-Dist: pycparser
Dynamic: author
Dynamic: author-email
Dynamic: classifier
Dynamic: description
Dynamic: description-content-type
Dynamic: home-page
Dynamic: license
Dynamic: license-file
Dynamic: project-url
Dynamic: requires-dist
Dynamic: summary
